my_django_starter/LICENSE
my_django_starter/__init__.py
my_django_starter/app_generalapp.py
my_django_starter/main.py
my_django_starter/__pycache__/__init__.cpython-310.pyc
my_django_starter/__pycache__/main.cpython-310.pyc
my_django_starter/animations/__init__.py
my_django_starter/animations/terminal_fx.py
my_django_starter/animations/__pycache__/__init__.cpython-310.pyc
my_django_starter/animations/__pycache__/terminal_fx.cpython-310.pyc
my_django_starter/builder/__init__.py
my_django_starter/builder/base.py
my_django_starter/builder/pipeline.py
my_django_starter/builder/__pycache__/__init__.cpython-310.pyc
my_django_starter/builder/__pycache__/base.cpython-310.pyc
my_django_starter/builder/__pycache__/pipeline.cpython-310.pyc
my_django_starter/modules/__init__.py
my_django_starter/modules/__pycache__/__init__.cpython-310.pyc
my_django_starter/modules/app_creator/__init__.py
my_django_starter/modules/app_creator/app_creator.py
my_django_starter/modules/app_creator/constants.py
my_django_starter/modules/app_creator/__pycache__/__init__.cpython-310.pyc
my_django_starter/modules/app_creator/__pycache__/app_creator.cpython-310.pyc
my_django_starter/modules/app_creator/__pycache__/constants.cpython-310.pyc
my_django_starter/modules/banner/__init__.py
my_django_starter/modules/banner/banner.py
my_django_starter/modules/banner/__pycache__/__init__.cpython-310.pyc
my_django_starter/modules/banner/__pycache__/banner.cpython-310.pyc
my_django_starter/modules/create_superuser/create_superuser.py
my_django_starter/modules/create_superuser/__pycache__/create_superuser.cpython-310.pyc
my_django_starter/modules/django_installer/__init__.py
my_django_starter/modules/django_installer/django_installer.py
my_django_starter/modules/django_installer/__pycache__/__init__.cpython-310.pyc
my_django_starter/modules/django_installer/__pycache__/django_installer.cpython-310.pyc
my_django_starter/modules/env_manager/__init__.py
my_django_starter/modules/env_manager/env_manager.py
my_django_starter-0.2.0.dist-info/METADATA
my_django_starter-0.2.0.dist-info/WHEEL
my_django_starter-0.2.0.dist-info/entry_points.txt
my_django_starter-0.2.0.dist-info/top_level.txt
my_django_starter-0.2.0.dist-info/RECORD
