Metadata-Version: 2.4
Name: my-django-starter
Version: 0.2.0
Summary: A starter kit to quickly scaffold Django projects.
Home-page: https://github.com/ChandraMohan-Sah/my-django-starter
Author: Chandra Mohan Sah
Author-email: csah9628@gmail.com
License: MIT
Project-URL: Bug Reports, https://github.com/ChandraMohan-Sah/my-django-starter/issues
Project-URL: Source, https://github.com/ChandraMohan-Sah/my-django-starter
Classifier: Programming Language :: Python :: 3
Classifier: Framework :: Django
Classifier: License :: OSI Approved :: MIT License
Classifier: Operating System :: OS Independent
Requires-Python: >=3.6
Requires-Dist: pyfiglet
Dynamic: author
Dynamic: author-email
Dynamic: classifier
Dynamic: description
Dynamic: description-content-type
Dynamic: home-page
Dynamic: license
Dynamic: project-url
Dynamic: requires-dist
Dynamic: requires-python
Dynamic: summary
